nlpjcd/__init__.py
nlpjcd/nlpjcd.py
nlpjcd-0.0.3.dist-info/LICENSE
nlpjcd-0.0.3.dist-info/METADATA
nlpjcd-0.0.3.dist-info/WHEEL
nlpjcd-0.0.3.dist-info/top_level.txt
nlpjcd-0.0.3.dist-info/RECORD
